odoo/addons/account_asset_pms/README.rst
odoo/addons/account_asset_pms/__init__.py
odoo/addons/account_asset_pms/__manifest__.py
odoo/addons/account_asset_pms/i18n/account_asset_pms.pot
odoo/addons/account_asset_pms/i18n/it.po
odoo/addons/account_asset_pms/models/__init__.py
odoo/addons/account_asset_pms/models/account_asset.py
odoo/addons/account_asset_pms/models/account_asset_line.py
odoo/addons/account_asset_pms/models/account_move.py
odoo/addons/account_asset_pms/readme/CONTRIBUTORS.rst
odoo/addons/account_asset_pms/readme/DESCRIPTION.rst
odoo/addons/account_asset_pms/readme/USAGE.rst
odoo/addons/account_asset_pms/report/__init__.py
odoo/addons/account_asset_pms/report/account_asset_report_xls.py
odoo/addons/account_asset_pms/static/description/icon.png
odoo/addons/account_asset_pms/static/description/index.html
odoo/addons/account_asset_pms/tests/__init__.py
odoo/addons/account_asset_pms/tests/test_account_asset_pms_property.py
odoo/addons/account_asset_pms/views/account_asset_view.xml
odoo14_addon_account_asset_pms-14.0.1.0.1.dev5.dist-info/METADATA
odoo14_addon_account_asset_pms-14.0.1.0.1.dev5.dist-info/WHEEL
odoo14_addon_account_asset_pms-14.0.1.0.1.dev5.dist-info/top_level.txt
odoo14_addon_account_asset_pms-14.0.1.0.1.dev5.dist-info/RECORD
